{
  "data": [
    {
      "year": 2011,
      "constructorId": 1,
      "constructor": "McLaren",
      "avg_duration_sec": 22.582109090909093,
      "total_stops": 110,
      "race_count": 19,
      "avg_stops_per_race": 5.7894736842105265,
      "color": "#FF8700",
      "circuitId": 1,
      "circuit": "Albert Park Grand Prix Circuit",
      "circuit_id": "albert-park-grand-prix-circuit"
    },
    {
      "year": 2011,
      "constructorId": 3,
      "constructor": "Williams",
      "avg_duration_sec": 23.699113402061855,
      "total_stops": 97,
      "race_count": 19,
      "avg_stops_per_race": 5.105263157894737,
      "color": "#005AFF",
      "circuitId": 1,
      "circuit": "Albert Park Grand Prix Circuit",
      "circuit_id": "albert-park-grand-prix-circuit"
    },
    {
      "year": 2011,
      "constructorId": 4,
      "constructor": "Renault",
      "avg_duration_sec": 23.239736263736265,
      "total_stops": 91,
      "race_count": 19,
      "avg_stops_per_race": 4.7894736842105265,
      "color": "#FFF500",
      "circuitId": 1,
      "circuit": "Albert Park Grand Prix Circuit",
      "circuit_id": "albert-park-grand-prix-circuit"
    },
    {
      "year": 2011,
      "constructorId": 5,
      "constructor": "Toro Rosso",
      "avg_duration_sec": 23.941404761904764,
      "total_stops": 84,
      "race_count": 18,
      "avg_stops_per_race": 4.666666666666667,
      "color": "#469BFF",
      "circuitId": 1,
      "circuit": "Albert Park Grand Prix Circuit",
      "circuit_id": "albert-park-grand-prix-circuit"
    },
    {
      "year": 2011,
      "constructorId": 6,
      "constructor": "Ferrari",
      "avg_duration_sec": 22.947407407407407,
      "total_stops": 108,
      "race_count": 19,
      "avg_stops_per_race": 5.684210526315789,
      "color": "#DC0000",
      "circuitId": 1,
      "circuit": "Albert Park Grand Prix Circuit",
      "circuit_id": "albert-park-grand-prix-circuit"
    },
    {
      "year": 2011,
      "constructorId": 9,
      "constructor": "Red Bull",
      "avg_duration_sec": 22.426548076923076,
      "total_stops": 104,
      "race_count": 19,
      "avg_stops_per_race": 5.473684210526316,
      "color": "#1E41FF",
      "circuitId": 1,
      "circuit": "Albert Park Grand Prix Circuit",
      "circuit_id": "albert-park-grand-prix-circuit"
    },
    {
      "year": 2011,
      "constructorId": 10,
      "constructor": "Force India",
      "avg_duration_sec": 23.236979381443298,
      "total_stops": 97,
      "race_count": 19,
      "avg_stops_per_race": 5.105263157894737,
      "color": "#F596C8",
      "circuitId": 1,
      "circuit": "Albert Park Grand Prix Circuit",
      "circuit_id": "albert-park-grand-prix-circuit"
    },
    {
      "year": 2011,
      "constructorId": 15,
      "constructor": "Sauber",
      "avg_duration_sec": 23.545123456790122,
      "total_stops": 81,
      "race_count": 19,
      "avg_stops_per_race": 4.2631578947368425,
      "color": "#52E252",
      "circuitId": 1,
      "circuit": "Albert Park Grand Prix Circuit",
      "circuit_id": "albert-park-grand-prix-circuit"
    },
    {
      "year": 2011,
      "constructorId": 131,
      "constructor": "Mercedes",
      "avg_duration_sec": 22.62519387755102,
      "total_stops": 98,
      "race_count": 19,
      "avg_stops_per_race": 5.157894736842105,
      "color": "#00D2BE",
      "circuitId": 1,
      "circuit": "Albert Park Grand Prix Circuit",
      "circuit_id": "albert-park-grand-prix-circuit"
    },
    {
      "year": 2011,
      "constructorId": 164,
      "constructor": "HRT",
      "avg_duration_sec": 38.95415853658537,
      "total_stops": 82,
      "race_count": 18,
      "avg_stops_per_race": 4.555555555555555,
      "color": "#888888",
      "circuitId": 2,
      "circuit": "Sepang International Circuit",
      "circuit_id": "sepang-international-circuit"
    },
    {
      "year": 2011,
      "constructorId": 166,
      "constructor": "Virgin",
      "avg_duration_sec": 24.236194805194806,
      "total_stops": 77,
      "race_count": 19,
      "avg_stops_per_race": 4.052631578947368,
      "color": "#888888",
      "circuitId": 1,
      "circuit": "Albert Park Grand Prix Circuit",
      "circuit_id": "albert-park-grand-prix-circuit"
    },
    {
      "year": 2011,
      "constructorId": 205,
      "constructor": "Lotus",
      "avg_duration_sec": 24.444211764705884,
      "total_stops": 85,
      "race_count": 18,
      "avg_stops_per_race": 4.722222222222222,
      "color": "#000000",
      "circuitId": 1,
      "circuit": "Albert Park Grand Prix Circuit",
      "circuit_id": "albert-park-grand-prix-circuit"
    },
    {
      "year": 2012,
      "constructorId": 1,
      "constructor": "McLaren",
      "avg_duration_sec": 22.594636363636365,
      "total_stops": 77,
      "race_count": 20,
      "avg_stops_per_race": 3.85,
      "color": "#FF8700",
      "circuitId": 1,
      "circuit": "Albert Park Grand Prix Circuit",
      "circuit_id": "albert-park-grand-prix-circuit"
    },
    {
      "year": 2012,
      "constructorId": 3,
      "constructor": "Williams",
      "avg_duration_sec": 23.52350666666667,
      "total_stops": 75,
      "race_count": 19,
      "avg_stops_per_race": 3.9473684210526314,
      "color": "#005AFF",
      "circuitId": 1,
      "circuit": "Albert Park Grand Prix Circuit",
      "circuit_id": "albert-park-grand-prix-circuit"
    },
    {
      "year": 2012,
      "constructorId": 5,
      "constructor": "Toro Rosso",
      "avg_duration_sec": 22.502449438202245,
      "total_stops": 89,
      "race_count": 20,
      "avg_stops_per_race": 4.45,
      "color": "#469BFF",
      "circuitId": 1,
      "circuit": "Albert Park Grand Prix Circuit",
      "circuit_id": "albert-park-grand-prix-circuit"
    },
    {
      "year": 2012,
      "constructorId": 6,
      "constructor": "Ferrari",
      "avg_duration_sec": 22.243654320987655,
      "total_stops": 81,
      "race_count": 20,
      "avg_stops_per_race": 4.05,
      "color": "#DC0000",
      "circuitId": 1,
      "circuit": "Albert Park Grand Prix Circuit",
      "circuit_id": "albert-park-grand-prix-circuit"
    },
    {
      "year": 2012,
      "constructorId": 9,
      "constructor": "Red Bull",
      "avg_duration_sec": 22.146623529411766,
      "total_stops": 85,
      "race_count": 20,
      "avg_stops_per_race": 4.25,
      "color": "#1E41FF",
      "circuitId": 1,
      "circuit": "Albert Park Grand Prix Circuit",
      "circuit_id": "albert-park-grand-prix-circuit"
    },
    {
      "year": 2012,
      "constructorId": 10,
      "constructor": "Force India",
      "avg_duration_sec": 22.69344155844156,
      "total_stops": 77,
      "race_count": 20,
      "avg_stops_per_race": 3.85,
      "color": "#F596C8",
      "circuitId": 1,
      "circuit": "Albert Park Grand Prix Circuit",
      "circuit_id": "albert-park-grand-prix-circuit"
    },
    {
      "year": 2012,
      "constructorId": 15,
      "constructor": "Sauber",
      "avg_duration_sec": 23.943573333333333,
      "total_stops": 75,
      "race_count": 20,
      "avg_stops_per_race": 3.75,
      "color": "#52E252",
      "circuitId": 1,
      "circuit": "Albert Park Grand Prix Circuit",
      "circuit_id": "albert-park-grand-prix-circuit"
    },
    {
      "year": 2012,
      "constructorId": 131,
      "constructor": "Mercedes",
      "avg_duration_sec": 22.462075000000002,
      "total_stops": 80,
      "race_count": 20,
      "avg_stops_per_race": 4.0,
      "color": "#00D2BE",
      "circuitId": 1,
      "circuit": "Albert Park Grand Prix Circuit",
      "circuit_id": "albert-park-grand-prix-circuit"
    },
    {
      "year": 2012,
      "constructorId": 164,
      "constructor": "HRT",
      "avg_duration_sec": 25.109176470588235,
      "total_stops": 68,
      "race_count": 18,
      "avg_stops_per_race": 3.7777777777777777,
      "color": "#888888",
      "circuitId": 2,
      "circuit": "Sepang International Circuit",
      "circuit_id": "sepang-international-circuit"
    },
    {
      "year": 2012,
      "constructorId": 206,
      "constructor": "Marussia",
      "avg_duration_sec": 24.50038157894737,
      "total_stops": 76,
      "race_count": 20,
      "avg_stops_per_race": 3.8,
      "color": "#888888",
      "circuitId": 1,
      "circuit": "Albert Park Grand Prix Circuit",
      "circuit_id": "albert-park-grand-prix-circuit"
    },
    {
      "year": 2012,
      "constructorId": 207,
      "constructor": "Caterham",
      "avg_duration_sec": 24.633473684210525,
      "total_stops": 95,
      "race_count": 20,
      "avg_stops_per_race": 4.75,
      "color": "#888888",
      "circuitId": 1,
      "circuit": "Albert Park Grand Prix Circuit",
      "circuit_id": "albert-park-grand-prix-circuit"
    },
    {
      "year": 2012,
      "constructorId": 208,
      "constructor": "Lotus F1",
      "avg_duration_sec": 23.319367647058826,
      "total_stops": 68,
      "race_count": 20,
      "avg_stops_per_race": 3.4,
      "color": "#F4F000",
      "circuitId": 1,
      "circuit": "Albert Park Grand Prix Circuit",
      "circuit_id": "albert-park-grand-prix-circuit"
    },
    {
      "year": 2013,
      "constructorId": 1,
      "constructor": "McLaren",
      "avg_duration_sec": 23.980325301204818,
      "total_stops": 83,
      "race_count": 19,
      "avg_stops_per_race": 4.368421052631579,
      "color": "#FF8700",
      "circuitId": 1,
      "circuit": "Albert Park Grand Prix Circuit",
      "circuit_id": "albert-park-grand-prix-circuit"
    },
    {
      "year": 2013,
      "constructorId": 3,
      "constructor": "Williams",
      "avg_duration_sec": 25.226593023255813,
      "total_stops": 86,
      "race_count": 19,
      "avg_stops_per_race": 4.526315789473684,
      "color": "#005AFF",
      "circuitId": 1,
      "circuit": "Albert Park Grand Prix Circuit",
      "circuit_id": "albert-park-grand-prix-circuit"
    },
    {
      "year": 2013,
      "constructorId": 5,
      "constructor": "Toro Rosso",
      "avg_duration_sec": 23.98368674698795,
      "total_stops": 83,
      "race_count": 19,
      "avg_stops_per_race": 4.368421052631579,
      "color": "#469BFF",
      "circuitId": 1,
      "circuit": "Albert Park Grand Prix Circuit",
      "circuit_id": "albert-park-grand-prix-circuit"
    },
    {
      "year": 2013,
      "constructorId": 6,
      "constructor": "Ferrari",
      "avg_duration_sec": 22.56878021978022,
      "total_stops": 91,
      "race_count": 19,
      "avg_stops_per_race": 4.7894736842105265,
      "color": "#DC0000",
      "circuitId": 1,
      "circuit": "Albert Park Grand Prix Circuit",
      "circuit_id": "albert-park-grand-prix-circuit"
    },
    {
      "year": 2013,
      "constructorId": 9,
      "constructor": "Red Bull",
      "avg_duration_sec": 24.073700000000002,
      "total_stops": 90,
      "race_count": 19,
      "avg_stops_per_race": 4.7368421052631575,
      "color": "#1E41FF",
      "circuitId": 1,
      "circuit": "Albert Park Grand Prix Circuit",
      "circuit_id": "albert-park-grand-prix-circuit"
    },
    {
      "year": 2013,
      "constructorId": 10,
      "constructor": "Force India",
      "avg_duration_sec": 27.38181333333333,
      "total_stops": 75,
      "race_count": 19,
      "avg_stops_per_race": 3.9473684210526314,
      "color": "#F596C8",
      "circuitId": 1,
      "circuit": "Albert Park Grand Prix Circuit",
      "circuit_id": "albert-park-grand-prix-circuit"
    },
    {
      "year": 2013,
      "constructorId": 15,
      "constructor": "Sauber",
      "avg_duration_sec": 23.275296703296704,
      "total_stops": 91,
      "race_count": 19,
      "avg_stops_per_race": 4.7894736842105265,
      "color": "#52E252",
      "circuitId": 1,
      "circuit": "Albert Park Grand Prix Circuit",
      "circuit_id": "albert-park-grand-prix-circuit"
    },
    {
      "year": 2013,
      "constructorId": 131,
      "constructor": "Mercedes",
      "avg_duration_sec": 22.642483516483516,
      "total_stops": 91,
      "race_count": 19,
      "avg_stops_per_race": 4.7894736842105265,
      "color": "#00D2BE",
      "circuitId": 1,
      "circuit": "Albert Park Grand Prix Circuit",
      "circuit_id": "albert-park-grand-prix-circuit"
    },
    {
      "year": 2013,
      "constructorId": 206,
      "constructor": "Marussia",
      "avg_duration_sec": 24.24308510638298,
      "total_stops": 94,
      "race_count": 19,
      "avg_stops_per_race": 4.947368421052632,
      "color": "#888888",
      "circuitId": 1,
      "circuit": "Albert Park Grand Prix Circuit",
      "circuit_id": "albert-park-grand-prix-circuit"
    },
    {
      "year": 2013,
      "constructorId": 207,
      "constructor": "Caterham",
      "avg_duration_sec": 24.465133333333334,
      "total_stops": 90,
      "race_count": 19,
      "avg_stops_per_race": 4.7368421052631575,
      "color": "#888888",
      "circuitId": 1,
      "circuit": "Albert Park Grand Prix Circuit",
      "circuit_id": "albert-park-grand-prix-circuit"
    },
    {
      "year": 2013,
      "constructorId": 208,
      "constructor": "Lotus F1",
      "avg_duration_sec": 24.098909090909093,
      "total_stops": 77,
      "race_count": 19,
      "avg_stops_per_race": 4.052631578947368,
      "color": "#F4F000",
      "circuitId": 1,
      "circuit": "Albert Park Grand Prix Circuit",
      "circuit_id": "albert-park-grand-prix-circuit"
    },
    {
      "year": 2014,
      "constructorId": 1,
      "constructor": "McLaren",
      "avg_duration_sec": 51.565158536585365,
      "total_stops": 82,
      "race_count": 19,
      "avg_stops_per_race": 4.315789473684211,
      "color": "#FF8700",
      "circuitId": 1,
      "circuit": "Albert Park Grand Prix Circuit",
      "circuit_id": "albert-park-grand-prix-circuit"
    },
    {
      "year": 2014,
      "constructorId": 3,
      "constructor": "Williams",
      "avg_duration_sec": 54.78976315789474,
      "total_stops": 76,
      "race_count": 19,
      "avg_stops_per_race": 4.0,
      "color": "#005AFF",
      "circuitId": 1,
      "circuit": "Albert Park Grand Prix Circuit",
      "circuit_id": "albert-park-grand-prix-circuit"
    },
    {
      "year": 2014,
      "constructorId": 5,
      "constructor": "Toro Rosso",
      "avg_duration_sec": 53.275074999999994,
      "total_stops": 80,
      "race_count": 19,
      "avg_stops_per_race": 4.2105263157894735,
      "color": "#469BFF",
      "circuitId": 1,
      "circuit": "Albert Park Grand Prix Circuit",
      "circuit_id": "albert-park-grand-prix-circuit"
    },
    {
      "year": 2014,
      "constructorId": 6,
      "constructor": "Ferrari",
      "avg_duration_sec": 51.47271951219512,
      "total_stops": 82,
      "race_count": 19,
      "avg_stops_per_race": 4.315789473684211,
      "color": "#DC0000",
      "circuitId": 1,
      "circuit": "Albert Park Grand Prix Circuit",
      "circuit_id": "albert-park-grand-prix-circuit"
    },
    {
      "year": 2014,
      "constructorId": 9,
      "constructor": "Red Bull",
      "avg_duration_sec": 53.07379012345679,
      "total_stops": 81,
      "race_count": 19,
      "avg_stops_per_race": 4.2631578947368425,
      "color": "#1E41FF",
      "circuitId": 1,
      "circuit": "Albert Park Grand Prix Circuit",
      "circuit_id": "albert-park-grand-prix-circuit"
    },
    {
      "year": 2014,
      "constructorId": 10,
      "constructor": "Force India",
      "avg_duration_sec": 57.008376811594204,
      "total_stops": 69,
      "race_count": 19,
      "avg_stops_per_race": 3.6315789473684212,
      "color": "#F596C8",
      "circuitId": 1,
      "circuit": "Albert Park Grand Prix Circuit",
      "circuit_id": "albert-park-grand-prix-circuit"
    },
    {
      "year": 2014,
      "constructorId": 15,
      "constructor": "Sauber",
      "avg_duration_sec": 54.67893506493507,
      "total_stops": 77,
      "race_count": 19,
      "avg_stops_per_race": 4.052631578947368,
      "color": "#52E252",
      "circuitId": 1,
      "circuit": "Albert Park Grand Prix Circuit",
      "circuit_id": "albert-park-grand-prix-circuit"
    },
    {
      "year": 2014,
      "constructorId": 131,
      "constructor": "Mercedes",
      "avg_duration_sec": 53.57614473684211,
      "total_stops": 76,
      "race_count": 19,
      "avg_stops_per_race": 4.0,
      "color": "#00D2BE",
      "circuitId": 1,
      "circuit": "Albert Park Grand Prix Circuit",
      "circuit_id": "albert-park-grand-prix-circuit"
    },
    {
      "year": 2014,
      "constructorId": 206,
      "constructor": "Marussia",
      "avg_duration_sec": 61.485460317460316,
      "total_stops": 63,
      "race_count": 15,
      "avg_stops_per_race": 4.2,
      "color": "#888888",
      "circuitId": 1,
      "circuit": "Albert Park Grand Prix Circuit",
      "circuit_id": "albert-park-grand-prix-circuit"
    },
    {
      "year": 2014,
      "constructorId": 207,
      "constructor": "Caterham",
      "avg_duration_sec": 64.889125,
      "total_stops": 56,
      "race_count": 16,
      "avg_stops_per_race": 3.5,
      "color": "#888888",
      "circuitId": 1,
      "circuit": "Albert Park Grand Prix Circuit",
      "circuit_id": "albert-park-grand-prix-circuit"
    },
    {
      "year": 2014,
      "constructorId": 208,
      "constructor": "Lotus F1",
      "avg_duration_sec": 54.799932432432435,
      "total_stops": 74,
      "race_count": 19,
      "avg_stops_per_race": 3.8947368421052633,
      "color": "#F4F000",
      "circuitId": 1,
      "circuit": "Albert Park Grand Prix Circuit",
      "circuit_id": "albert-park-grand-prix-circuit"
    },
    {
      "year": 2015,
      "constructorId": 1,
      "constructor": "McLaren",
      "avg_duration_sec": 25.843824324324324,
      "total_stops": 74,
      "race_count": 19,
      "avg_stops_per_race": 3.8947368421052633,
      "color": "#FF8700",
      "circuitId": 1,
      "circuit": "Albert Park Grand Prix Circuit",
      "circuit_id": "albert-park-grand-prix-circuit"
    },
    {
      "year": 2015,
      "constructorId": 3,
      "constructor": "Williams",
      "avg_duration_sec": 25.145569620253166,
      "total_stops": 79,
      "race_count": 19,
      "avg_stops_per_race": 4.157894736842105,
      "color": "#005AFF",
      "circuitId": 1,
      "circuit": "Albert Park Grand Prix Circuit",
      "circuit_id": "albert-park-grand-prix-circuit"
    },
    {
      "year": 2015,
      "constructorId": 5,
      "constructor": "Toro Rosso",
      "avg_duration_sec": 26.43996052631579,
      "total_stops": 76,
      "race_count": 19,
      "avg_stops_per_race": 4.0,
      "color": "#469BFF",
      "circuitId": 1,
      "circuit": "Albert Park Grand Prix Circuit",
      "circuit_id": "albert-park-grand-prix-circuit"
    },
    {
      "year": 2015,
      "constructorId": 6,
      "constructor": "Ferrari",
      "avg_duration_sec": 25.148109589041095,
      "total_stops": 73,
      "race_count": 19,
      "avg_stops_per_race": 3.8421052631578947,
      "color": "#DC0000",
      "circuitId": 1,
      "circuit": "Albert Park Grand Prix Circuit",
      "circuit_id": "albert-park-grand-prix-circuit"
    },
    {
      "year": 2015,
      "constructorId": 9,
      "constructor": "Red Bull",
      "avg_duration_sec": 24.77613698630137,
      "total_stops": 73,
      "race_count": 19,
      "avg_stops_per_race": 3.8421052631578947,
      "color": "#1E41FF",
      "circuitId": 1,
      "circuit": "Albert Park Grand Prix Circuit",
      "circuit_id": "albert-park-grand-prix-circuit"
    },
    {
      "year": 2015,
      "constructorId": 10,
      "constructor": "Force India",
      "avg_duration_sec": 25.3163,
      "total_stops": 70,
      "race_count": 19,
      "avg_stops_per_race": 3.6842105263157894,
      "color": "#F596C8",
      "circuitId": 1,
      "circuit": "Albert Park Grand Prix Circuit",
      "circuit_id": "albert-park-grand-prix-circuit"
    },
    {
      "year": 2015,
      "constructorId": 15,
      "constructor": "Sauber",
      "avg_duration_sec": 25.331172413793105,
      "total_stops": 87,
      "race_count": 19,
      "avg_stops_per_race": 4.578947368421052,
      "color": "#52E252",
      "circuitId": 1,
      "circuit": "Albert Park Grand Prix Circuit",
      "circuit_id": "albert-park-grand-prix-circuit"
    },
    {
      "year": 2015,
      "constructorId": 131,
      "constructor": "Mercedes",
      "avg_duration_sec": 23.81149333333333,
      "total_stops": 75,
      "race_count": 19,
      "avg_stops_per_race": 3.9473684210526314,
      "color": "#00D2BE",
      "circuitId": 1,
      "circuit": "Albert Park Grand Prix Circuit",
      "circuit_id": "albert-park-grand-prix-circuit"
    },
    {
      "year": 2015,
      "constructorId": 208,
      "constructor": "Lotus F1",
      "avg_duration_sec": 26.60062121212121,
      "total_stops": 66,
      "race_count": 16,
      "avg_stops_per_race": 4.125,
      "color": "#F4F000",
      "circuitId": 2,
      "circuit": "Sepang International Circuit",
      "circuit_id": "sepang-international-circuit"
    },
    {
      "year": 2015,
      "constructorId": 209,
      "constructor": "Manor Marussia",
      "avg_duration_sec": 26.84341176470588,
      "total_stops": 68,
      "race_count": 18,
      "avg_stops_per_race": 3.7777777777777777,
      "color": "#888888",
      "circuitId": 2,
      "circuit": "Sepang International Circuit",
      "circuit_id": "sepang-international-circuit"
    },
    {
      "year": 2016,
      "constructorId": 1,
      "constructor": "McLaren",
      "avg_duration_sec": 123.15217777777778,
      "total_stops": 90,
      "race_count": 21,
      "avg_stops_per_race": 4.285714285714286,
      "color": "#FF8700",
      "circuitId": 1,
      "circuit": "Albert Park Grand Prix Circuit",
      "circuit_id": "albert-park-grand-prix-circuit"
    },
    {
      "year": 2016,
      "constructorId": 3,
      "constructor": "Williams",
      "avg_duration_sec": 141.237,
      "total_stops": 94,
      "race_count": 21,
      "avg_stops_per_race": 4.476190476190476,
      "color": "#005AFF",
      "circuitId": 1,
      "circuit": "Albert Park Grand Prix Circuit",
      "circuit_id": "albert-park-grand-prix-circuit"
    },
    {
      "year": 2016,
      "constructorId": 4,
      "constructor": "Renault",
      "avg_duration_sec": 98.56385057471265,
      "total_stops": 87,
      "race_count": 21,
      "avg_stops_per_race": 4.142857142857143,
      "color": "#FFF500",
      "circuitId": 1,
      "circuit": "Albert Park Grand Prix Circuit",
      "circuit_id": "albert-park-grand-prix-circuit"
    },
    {
      "year": 2016,
      "constructorId": 5,
      "constructor": "Toro Rosso",
      "avg_duration_sec": 135.61536263736264,
      "total_stops": 91,
      "race_count": 21,
      "avg_stops_per_race": 4.333333333333333,
      "color": "#469BFF",
      "circuitId": 1,
      "circuit": "Albert Park Grand Prix Circuit",
      "circuit_id": "albert-park-grand-prix-circuit"
    },
    {
      "year": 2016,
      "constructorId": 6,
      "constructor": "Ferrari",
      "avg_duration_sec": 111.51469767441861,
      "total_stops": 86,
      "race_count": 21,
      "avg_stops_per_race": 4.095238095238095,
      "color": "#DC0000",
      "circuitId": 1,
      "circuit": "Albert Park Grand Prix Circuit",
      "circuit_id": "albert-park-grand-prix-circuit"
    },
    {
      "year": 2016,
      "constructorId": 9,
      "constructor": "Red Bull",
      "avg_duration_sec": 118.80983809523809,
      "total_stops": 105,
      "race_count": 21,
      "avg_stops_per_race": 5.0,
      "color": "#1E41FF",
      "circuitId": 1,
      "circuit": "Albert Park Grand Prix Circuit",
      "circuit_id": "albert-park-grand-prix-circuit"
    },
    {
      "year": 2016,
      "constructorId": 10,
      "constructor": "Force India",
      "avg_duration_sec": 145.8643,
      "total_stops": 90,
      "race_count": 21,
      "avg_stops_per_race": 4.285714285714286,
      "color": "#F596C8",
      "circuitId": 1,
      "circuit": "Albert Park Grand Prix Circuit",
      "circuit_id": "albert-park-grand-prix-circuit"
    },
    {
      "year": 2016,
      "constructorId": 15,
      "constructor": "Sauber",
      "avg_duration_sec": 110.50818390804598,
      "total_stops": 87,
      "race_count": 21,
      "avg_stops_per_race": 4.142857142857143,
      "color": "#52E252",
      "circuitId": 1,
      "circuit": "Albert Park Grand Prix Circuit",
      "circuit_id": "albert-park-grand-prix-circuit"
    },
    {
      "year": 2016,
      "constructorId": 131,
      "constructor": "Mercedes",
      "avg_duration_sec": 152.80671764705883,
      "total_stops": 85,
      "race_count": 20,
      "avg_stops_per_race": 4.25,
      "color": "#00D2BE",
      "circuitId": 1,
      "circuit": "Albert Park Grand Prix Circuit",
      "circuit_id": "albert-park-grand-prix-circuit"
    },
    {
      "year": 2016,
      "constructorId": 209,
      "constructor": "Manor Marussia",
      "avg_duration_sec": 128.2121022727273,
      "total_stops": 88,
      "race_count": 21,
      "avg_stops_per_race": 4.190476190476191,
      "color": "#888888",
      "circuitId": 1,
      "circuit": "Albert Park Grand Prix Circuit",
      "circuit_id": "albert-park-grand-prix-circuit"
    },
    {
      "year": 2016,
      "constructorId": 210,
      "constructor": "Haas F1 Team",
      "avg_duration_sec": 100.40355813953488,
      "total_stops": 86,
      "race_count": 21,
      "avg_stops_per_race": 4.095238095238095,
      "color": "#B6BABD",
      "circuitId": 1,
      "circuit": "Albert Park Grand Prix Circuit",
      "circuit_id": "albert-park-grand-prix-circuit"
    },
    {
      "year": 2017,
      "constructorId": 1,
      "constructor": "McLaren",
      "avg_duration_sec": 65.02057142857143,
      "total_stops": 63,
      "race_count": 20,
      "avg_stops_per_race": 3.15,
      "color": "#FF8700",
      "circuitId": 1,
      "circuit": "Albert Park Grand Prix Circuit",
      "circuit_id": "albert-park-grand-prix-circuit"
    },
    {
      "year": 2017,
      "constructorId": 3,
      "constructor": "Williams",
      "avg_duration_sec": 57.52492207792208,
      "total_stops": 77,
      "race_count": 20,
      "avg_stops_per_race": 3.85,
      "color": "#005AFF",
      "circuitId": 1,
      "circuit": "Albert Park Grand Prix Circuit",
      "circuit_id": "albert-park-grand-prix-circuit"
    },
    {
      "year": 2017,
      "constructorId": 4,
      "constructor": "Renault",
      "avg_duration_sec": 43.83502941176471,
      "total_stops": 68,
      "race_count": 20,
      "avg_stops_per_race": 3.4,
      "color": "#FFF500",
      "circuitId": 1,
      "circuit": "Albert Park Grand Prix Circuit",
      "circuit_id": "albert-park-grand-prix-circuit"
    },
    {
      "year": 2017,
      "constructorId": 5,
      "constructor": "Toro Rosso",
      "avg_duration_sec": 44.30386363636364,
      "total_stops": 66,
      "race_count": 20,
      "avg_stops_per_race": 3.3,
      "color": "#469BFF",
      "circuitId": 1,
      "circuit": "Albert Park Grand Prix Circuit",
      "circuit_id": "albert-park-grand-prix-circuit"
    },
    {
      "year": 2017,
      "constructorId": 6,
      "constructor": "Ferrari",
      "avg_duration_sec": 66.23237878787879,
      "total_stops": 66,
      "race_count": 19,
      "avg_stops_per_race": 3.473684210526316,
      "color": "#DC0000",
      "circuitId": 1,
      "circuit": "Albert Park Grand Prix Circuit",
      "circuit_id": "albert-park-grand-prix-circuit"
    },
    {
      "year": 2017,
      "constructorId": 9,
      "constructor": "Red Bull",
      "avg_duration_sec": 46.23035087719298,
      "total_stops": 57,
      "race_count": 20,
      "avg_stops_per_race": 2.85,
      "color": "#1E41FF",
      "circuitId": 1,
      "circuit": "Albert Park Grand Prix Circuit",
      "circuit_id": "albert-park-grand-prix-circuit"
    },
    {
      "year": 2017,
      "constructorId": 10,
      "constructor": "Force India",
      "avg_duration_sec": 60.34551898734177,
      "total_stops": 79,
      "race_count": 20,
      "avg_stops_per_race": 3.95,
      "color": "#F596C8",
      "circuitId": 1,
      "circuit": "Albert Park Grand Prix Circuit",
      "circuit_id": "albert-park-grand-prix-circuit"
    },
    {
      "year": 2017,
      "constructorId": 15,
      "constructor": "Sauber",
      "avg_duration_sec": 62.402767123287674,
      "total_stops": 73,
      "race_count": 20,
      "avg_stops_per_race": 3.65,
      "color": "#52E252",
      "circuitId": 1,
      "circuit": "Albert Park Grand Prix Circuit",
      "circuit_id": "albert-park-grand-prix-circuit"
    },
    {
      "year": 2017,
      "constructorId": 131,
      "constructor": "Mercedes",
      "avg_duration_sec": 59.76212676056338,
      "total_stops": 71,
      "race_count": 20,
      "avg_stops_per_race": 3.55,
      "color": "#00D2BE",
      "circuitId": 1,
      "circuit": "Albert Park Grand Prix Circuit",
      "circuit_id": "albert-park-grand-prix-circuit"
    },
    {
      "year": 2017,
      "constructorId": 210,
      "constructor": "Haas F1 Team",
      "avg_duration_sec": 59.583351351351354,
      "total_stops": 74,
      "race_count": 20,
      "avg_stops_per_race": 3.7,
      "color": "#B6BABD",
      "circuitId": 1,
      "circuit": "Albert Park Grand Prix Circuit",
      "circuit_id": "albert-park-grand-prix-circuit"
    },
    {
      "year": 2018,
      "constructorId": 1,
      "constructor": "McLaren",
      "avg_duration_sec": 25.363385964912283,
      "total_stops": 57,
      "race_count": 21,
      "avg_stops_per_race": 2.7142857142857144,
      "color": "#FF8700",
      "circuitId": 1,
      "circuit": "Albert Park Grand Prix Circuit",
      "circuit_id": "albert-park-grand-prix-circuit"
    },
    {
      "year": 2018,
      "constructorId": 3,
      "constructor": "Williams",
      "avg_duration_sec": 24.819171875,
      "total_stops": 64,
      "race_count": 21,
      "avg_stops_per_race": 3.0476190476190474,
      "color": "#005AFF",
      "circuitId": 1,
      "circuit": "Albert Park Grand Prix Circuit",
      "circuit_id": "albert-park-grand-prix-circuit"
    },
    {
      "year": 2018,
      "constructorId": 4,
      "constructor": "Renault",
      "avg_duration_sec": 24.20658823529412,
      "total_stops": 51,
      "race_count": 21,
      "avg_stops_per_race": 2.4285714285714284,
      "color": "#FFF500",
      "circuitId": 1,
      "circuit": "Albert Park Grand Prix Circuit",
      "circuit_id": "albert-park-grand-prix-circuit"
    },
    {
      "year": 2018,
      "constructorId": 5,
      "constructor": "Toro Rosso",
      "avg_duration_sec": 24.386326923076922,
      "total_stops": 52,
      "race_count": 21,
      "avg_stops_per_race": 2.4761904761904763,
      "color": "#469BFF",
      "circuitId": 1,
      "circuit": "Albert Park Grand Prix Circuit",
      "circuit_id": "albert-park-grand-prix-circuit"
    },
    {
      "year": 2018,
      "constructorId": 6,
      "constructor": "Ferrari",
      "avg_duration_sec": 24.72264150943396,
      "total_stops": 53,
      "race_count": 21,
      "avg_stops_per_race": 2.5238095238095237,
      "color": "#DC0000",
      "circuitId": 1,
      "circuit": "Albert Park Grand Prix Circuit",
      "circuit_id": "albert-park-grand-prix-circuit"
    },
    {
      "year": 2018,
      "constructorId": 9,
      "constructor": "Red Bull",
      "avg_duration_sec": 23.778391304347828,
      "total_stops": 46,
      "race_count": 21,
      "avg_stops_per_race": 2.1904761904761907,
      "color": "#1E41FF",
      "circuitId": 1,
      "circuit": "Albert Park Grand Prix Circuit",
      "circuit_id": "albert-park-grand-prix-circuit"
    },
    {
      "year": 2018,
      "constructorId": 10,
      "constructor": "Force India",
      "avg_duration_sec": 25.17796153846154,
      "total_stops": 52,
      "race_count": 20,
      "avg_stops_per_race": 2.6,
      "color": "#F596C8",
      "circuitId": 1,
      "circuit": "Albert Park Grand Prix Circuit",
      "circuit_id": "albert-park-grand-prix-circuit"
    },
    {
      "year": 2018,
      "constructorId": 15,
      "constructor": "Sauber",
      "avg_duration_sec": 25.174259999999997,
      "total_stops": 50,
      "race_count": 21,
      "avg_stops_per_race": 2.380952380952381,
      "color": "#52E252",
      "circuitId": 1,
      "circuit": "Albert Park Grand Prix Circuit",
      "circuit_id": "albert-park-grand-prix-circuit"
    },
    {
      "year": 2018,
      "constructorId": 131,
      "constructor": "Mercedes",
      "avg_duration_sec": 23.67211111111111,
      "total_stops": 54,
      "race_count": 21,
      "avg_stops_per_race": 2.5714285714285716,
      "color": "#00D2BE",
      "circuitId": 1,
      "circuit": "Albert Park Grand Prix Circuit",
      "circuit_id": "albert-park-grand-prix-circuit"
    },
    {
      "year": 2018,
      "constructorId": 210,
      "constructor": "Haas F1 Team",
      "avg_duration_sec": 25.233052631578946,
      "total_stops": 57,
      "race_count": 21,
      "avg_stops_per_race": 2.7142857142857144,
      "color": "#B6BABD",
      "circuitId": 1,
      "circuit": "Albert Park Grand Prix Circuit",
      "circuit_id": "albert-park-grand-prix-circuit"
    },
    {
      "year": 2019,
      "constructorId": 1,
      "constructor": "McLaren",
      "avg_duration_sec": 26.156410714285713,
      "total_stops": 56,
      "race_count": 21,
      "avg_stops_per_race": 2.6666666666666665,
      "color": "#FF8700",
      "circuitId": 1,
      "circuit": "Albert Park Grand Prix Circuit",
      "circuit_id": "albert-park-grand-prix-circuit"
    },
    {
      "year": 2019,
      "constructorId": 3,
      "constructor": "Williams",
      "avg_duration_sec": 24.47635135135135,
      "total_stops": 74,
      "race_count": 21,
      "avg_stops_per_race": 3.5238095238095237,
      "color": "#005AFF",
      "circuitId": 1,
      "circuit": "Albert Park Grand Prix Circuit",
      "circuit_id": "albert-park-grand-prix-circuit"
    },
    {
      "year": 2019,
      "constructorId": 4,
      "constructor": "Renault",
      "avg_duration_sec": 24.96535714285714,
      "total_stops": 56,
      "race_count": 21,
      "avg_stops_per_race": 2.6666666666666665,
      "color": "#FFF500",
      "circuitId": 1,
      "circuit": "Albert Park Grand Prix Circuit",
      "circuit_id": "albert-park-grand-prix-circuit"
    },
    {
      "year": 2019,
      "constructorId": 5,
      "constructor": "Toro Rosso",
      "avg_duration_sec": 25.412629032258064,
      "total_stops": 62,
      "race_count": 21,
      "avg_stops_per_race": 2.9523809523809526,
      "color": "#469BFF",
      "circuitId": 1,
      "circuit": "Albert Park Grand Prix Circuit",
      "circuit_id": "albert-park-grand-prix-circuit"
    },
    {
      "year": 2019,
      "constructorId": 6,
      "constructor": "Ferrari",
      "avg_duration_sec": 24.616410958904112,
      "total_stops": 73,
      "race_count": 21,
      "avg_stops_per_race": 3.4761904761904763,
      "color": "#DC0000",
      "circuitId": 1,
      "circuit": "Albert Park Grand Prix Circuit",
      "circuit_id": "albert-park-grand-prix-circuit"
    },
    {
      "year": 2019,
      "constructorId": 9,
      "constructor": "Red Bull",
      "avg_duration_sec": 23.971938461538464,
      "total_stops": 65,
      "race_count": 21,
      "avg_stops_per_race": 3.0952380952380953,
      "color": "#1E41FF",
      "circuitId": 1,
      "circuit": "Albert Park Grand Prix Circuit",
      "circuit_id": "albert-park-grand-prix-circuit"
    },
    {
      "year": 2019,
      "constructorId": 51,
      "constructor": "Alfa Romeo",
      "avg_duration_sec": 25.700426470588233,
      "total_stops": 68,
      "race_count": 21,
      "avg_stops_per_race": 3.238095238095238,
      "color": "#900000",
      "circuitId": 1,
      "circuit": "Albert Park Grand Prix Circuit",
      "circuit_id": "albert-park-grand-prix-circuit"
    },
    {
      "year": 2019,
      "constructorId": 131,
      "constructor": "Mercedes",
      "avg_duration_sec": 24.60295588235294,
      "total_stops": 68,
      "race_count": 21,
      "avg_stops_per_race": 3.238095238095238,
      "color": "#00D2BE",
      "circuitId": 1,
      "circuit": "Albert Park Grand Prix Circuit",
      "circuit_id": "albert-park-grand-prix-circuit"
    },
    {
      "year": 2019,
      "constructorId": 210,
      "constructor": "Haas F1 Team",
      "avg_duration_sec": 24.471939393939394,
      "total_stops": 66,
      "race_count": 21,
      "avg_stops_per_race": 3.142857142857143,
      "color": "#B6BABD",
      "circuitId": 1,
      "circuit": "Albert Park Grand Prix Circuit",
      "circuit_id": "albert-park-grand-prix-circuit"
    },
    {
      "year": 2019,
      "constructorId": 211,
      "constructor": "Racing Point",
      "avg_duration_sec": 25.31364516129032,
      "total_stops": 62,
      "race_count": 21,
      "avg_stops_per_race": 2.9523809523809526,
      "color": "#F596C8",
      "circuitId": 1,
      "circuit": "Albert Park Grand Prix Circuit",
      "circuit_id": "albert-park-grand-prix-circuit"
    },
    {
      "year": 2020,
      "constructorId": 1,
      "constructor": "McLaren",
      "avg_duration_sec": 153.44751612903227,
      "total_stops": 62,
      "race_count": 17,
      "avg_stops_per_race": 3.6470588235294117,
      "color": "#FF8700",
      "circuitId": 70,
      "circuit": "Red Bull Ring",
      "circuit_id": "red-bull-ring"
    },
    {
      "year": 2020,
      "constructorId": 3,
      "constructor": "Williams",
      "avg_duration_sec": 147.67023076923078,
      "total_stops": 65,
      "race_count": 17,
      "avg_stops_per_race": 3.823529411764706,
      "color": "#005AFF",
      "circuitId": 70,
      "circuit": "Red Bull Ring",
      "circuit_id": "red-bull-ring"
    },
    {
      "year": 2020,
      "constructorId": 4,
      "constructor": "Renault",
      "avg_duration_sec": 183.8254,
      "total_stops": 50,
      "race_count": 17,
      "avg_stops_per_race": 2.9411764705882355,
      "color": "#FFF500",
      "circuitId": 70,
      "circuit": "Red Bull Ring",
      "circuit_id": "red-bull-ring"
    },
    {
      "year": 2020,
      "constructorId": 6,
      "constructor": "Ferrari",
      "avg_duration_sec": 154.11018644067798,
      "total_stops": 59,
      "race_count": 17,
      "avg_stops_per_race": 3.4705882352941178,
      "color": "#DC0000",
      "circuitId": 70,
      "circuit": "Red Bull Ring",
      "circuit_id": "red-bull-ring"
    },
    {
      "year": 2020,
      "constructorId": 9,
      "constructor": "Red Bull",
      "avg_duration_sec": 155.20303278688525,
      "total_stops": 61,
      "race_count": 17,
      "avg_stops_per_race": 3.588235294117647,
      "color": "#1E41FF",
      "circuitId": 70,
      "circuit": "Red Bull Ring",
      "circuit_id": "red-bull-ring"
    },
    {
      "year": 2020,
      "constructorId": 51,
      "constructor": "Alfa Romeo",
      "avg_duration_sec": 154.48754098360658,
      "total_stops": 61,
      "race_count": 17,
      "avg_stops_per_race": 3.588235294117647,
      "color": "#900000",
      "circuitId": 70,
      "circuit": "Red Bull Ring",
      "circuit_id": "red-bull-ring"
    },
    {
      "year": 2020,
      "constructorId": 131,
      "constructor": "Mercedes",
      "avg_duration_sec": 177.11904285714286,
      "total_stops": 70,
      "race_count": 17,
      "avg_stops_per_race": 4.117647058823529,
      "color": "#00D2BE",
      "circuitId": 70,
      "circuit": "Red Bull Ring",
      "circuit_id": "red-bull-ring"
    },
    {
      "year": 2020,
      "constructorId": 210,
      "constructor": "Haas F1 Team",
      "avg_duration_sec": 127.48758490566037,
      "total_stops": 53,
      "race_count": 17,
      "avg_stops_per_race": 3.1176470588235294,
      "color": "#B6BABD",
      "circuitId": 70,
      "circuit": "Red Bull Ring",
      "circuit_id": "red-bull-ring"
    },
    {
      "year": 2020,
      "constructorId": 211,
      "constructor": "Racing Point",
      "avg_duration_sec": 192.52596428571428,
      "total_stops": 56,
      "race_count": 17,
      "avg_stops_per_race": 3.2941176470588234,
      "color": "#F596C8",
      "circuitId": 70,
      "circuit": "Red Bull Ring",
      "circuit_id": "red-bull-ring"
    },
    {
      "year": 2020,
      "constructorId": 213,
      "constructor": "AlphaTauri",
      "avg_duration_sec": 164.46868421052633,
      "total_stops": 57,
      "race_count": 17,
      "avg_stops_per_race": 3.3529411764705883,
      "color": "#2B4562",
      "circuitId": 70,
      "circuit": "Red Bull Ring",
      "circuit_id": "red-bull-ring"
    },
    {
      "year": 2021,
      "constructorId": 1,
      "constructor": "McLaren",
      "avg_duration_sec": 241.3371948051948,
      "total_stops": 77,
      "race_count": 21,
      "avg_stops_per_race": 3.6666666666666665,
      "color": "#FF8700",
      "circuitId": 3,
      "circuit": "Bahrain International Circuit",
      "circuit_id": "bahrain-international-circuit"
    },
    {
      "year": 2021,
      "constructorId": 3,
      "constructor": "Williams",
      "avg_duration_sec": 210.03517105263157,
      "total_stops": 76,
      "race_count": 21,
      "avg_stops_per_race": 3.619047619047619,
      "color": "#005AFF",
      "circuitId": 3,
      "circuit": "Bahrain International Circuit",
      "circuit_id": "bahrain-international-circuit"
    },
    {
      "year": 2021,
      "constructorId": 6,
      "constructor": "Ferrari",
      "avg_duration_sec": 249.91687837837839,
      "total_stops": 74,
      "race_count": 21,
      "avg_stops_per_race": 3.5238095238095237,
      "color": "#DC0000",
      "circuitId": 3,
      "circuit": "Bahrain International Circuit",
      "circuit_id": "bahrain-international-circuit"
    },
    {
      "year": 2021,
      "constructorId": 9,
      "constructor": "Red Bull",
      "avg_duration_sec": 159.19313953488373,
      "total_stops": 86,
      "race_count": 21,
      "avg_stops_per_race": 4.095238095238095,
      "color": "#1E41FF",
      "circuitId": 3,
      "circuit": "Bahrain International Circuit",
      "circuit_id": "bahrain-international-circuit"
    },
    {
      "year": 2021,
      "constructorId": 51,
      "constructor": "Alfa Romeo",
      "avg_duration_sec": 242.8414096385542,
      "total_stops": 83,
      "race_count": 21,
      "avg_stops_per_race": 3.9523809523809526,
      "color": "#900000",
      "circuitId": 3,
      "circuit": "Bahrain International Circuit",
      "circuit_id": "bahrain-international-circuit"
    },
    {
      "year": 2021,
      "constructorId": 117,
      "constructor": "Aston Martin",
      "avg_duration_sec": 211.6535,
      "total_stops": 78,
      "race_count": 21,
      "avg_stops_per_race": 3.7142857142857144,
      "color": "#006F62",
      "circuitId": 3,
      "circuit": "Bahrain International Circuit",
      "circuit_id": "bahrain-international-circuit"
    },
    {
      "year": 2021,
      "constructorId": 131,
      "constructor": "Mercedes",
      "avg_duration_sec": 199.0737441860465,
      "total_stops": 86,
      "race_count": 21,
      "avg_stops_per_race": 4.095238095238095,
      "color": "#00D2BE",
      "circuitId": 3,
      "circuit": "Bahrain International Circuit",
      "circuit_id": "bahrain-international-circuit"
    },
    {
      "year": 2021,
      "constructorId": 210,
      "constructor": "Haas F1 Team",
      "avg_duration_sec": 206.68368292682928,
      "total_stops": 82,
      "race_count": 21,
      "avg_stops_per_race": 3.9047619047619047,
      "color": "#B6BABD",
      "circuitId": 3,
      "circuit": "Bahrain International Circuit",
      "circuit_id": "bahrain-international-circuit"
    },
    {
      "year": 2021,
      "constructorId": 213,
      "constructor": "AlphaTauri",
      "avg_duration_sec": 244.38274390243902,
      "total_stops": 82,
      "race_count": 20,
      "avg_stops_per_race": 4.1,
      "color": "#2B4562",
      "circuitId": 3,
      "circuit": "Bahrain International Circuit",
      "circuit_id": "bahrain-international-circuit"
    },
    {
      "year": 2021,
      "constructorId": 214,
      "constructor": "Alpine F1 Team",
      "avg_duration_sec": 241.3245810810811,
      "total_stops": 74,
      "race_count": 21,
      "avg_stops_per_race": 3.5238095238095237,
      "color": "#0090FF",
      "circuitId": 3,
      "circuit": "Bahrain International Circuit",
      "circuit_id": "bahrain-international-circuit"
    },
    {
      "year": 2022,
      "constructorId": 1,
      "constructor": "McLaren",
      "avg_duration_sec": 133.05577380952383,
      "total_stops": 84,
      "race_count": 22,
      "avg_stops_per_race": 3.8181818181818183,
      "color": "#FF8700",
      "circuitId": 3,
      "circuit": "Bahrain International Circuit",
      "circuit_id": "bahrain-international-circuit"
    },
    {
      "year": 2022,
      "constructorId": 3,
      "constructor": "Williams",
      "avg_duration_sec": 90.469091954023,
      "total_stops": 87,
      "race_count": 21,
      "avg_stops_per_race": 4.142857142857143,
      "color": "#005AFF",
      "circuitId": 3,
      "circuit": "Bahrain International Circuit",
      "circuit_id": "bahrain-international-circuit"
    },
    {
      "year": 2022,
      "constructorId": 6,
      "constructor": "Ferrari",
      "avg_duration_sec": 135.7167435897436,
      "total_stops": 78,
      "race_count": 22,
      "avg_stops_per_race": 3.5454545454545454,
      "color": "#DC0000",
      "circuitId": 3,
      "circuit": "Bahrain International Circuit",
      "circuit_id": "bahrain-international-circuit"
    },
    {
      "year": 2022,
      "constructorId": 9,
      "constructor": "Red Bull",
      "avg_duration_sec": 125.7036966292135,
      "total_stops": 89,
      "race_count": 22,
      "avg_stops_per_race": 4.045454545454546,
      "color": "#1E41FF",
      "circuitId": 3,
      "circuit": "Bahrain International Circuit",
      "circuit_id": "bahrain-international-circuit"
    },
    {
      "year": 2022,
      "constructorId": 51,
      "constructor": "Alfa Romeo",
      "avg_duration_sec": 116.41223880597015,
      "total_stops": 67,
      "race_count": 22,
      "avg_stops_per_race": 3.0454545454545454,
      "color": "#900000",
      "circuitId": 3,
      "circuit": "Bahrain International Circuit",
      "circuit_id": "bahrain-international-circuit"
    },
    {
      "year": 2022,
      "constructorId": 117,
      "constructor": "Aston Martin",
      "avg_duration_sec": 137.07575308641975,
      "total_stops": 81,
      "race_count": 22,
      "avg_stops_per_race": 3.6818181818181817,
      "color": "#006F62",
      "circuitId": 3,
      "circuit": "Bahrain International Circuit",
      "circuit_id": "bahrain-international-circuit"
    },
    {
      "year": 2022,
      "constructorId": 131,
      "constructor": "Mercedes",
      "avg_duration_sec": 99.78285185185186,
      "total_stops": 81,
      "race_count": 22,
      "avg_stops_per_race": 3.6818181818181817,
      "color": "#00D2BE",
      "circuitId": 3,
      "circuit": "Bahrain International Circuit",
      "circuit_id": "bahrain-international-circuit"
    },
    {
      "year": 2022,
      "constructorId": 210,
      "constructor": "Haas F1 Team",
      "avg_duration_sec": 115.88494736842105,
      "total_stops": 76,
      "race_count": 22,
      "avg_stops_per_race": 3.4545454545454546,
      "color": "#B6BABD",
      "circuitId": 3,
      "circuit": "Bahrain International Circuit",
      "circuit_id": "bahrain-international-circuit"
    },
    {
      "year": 2022,
      "constructorId": 213,
      "constructor": "AlphaTauri",
      "avg_duration_sec": 127.97272727272728,
      "total_stops": 88,
      "race_count": 22,
      "avg_stops_per_race": 4.0,
      "color": "#2B4562",
      "circuitId": 3,
      "circuit": "Bahrain International Circuit",
      "circuit_id": "bahrain-international-circuit"
    },
    {
      "year": 2022,
      "constructorId": 214,
      "constructor": "Alpine F1 Team",
      "avg_duration_sec": 145.9109054054054,
      "total_stops": 74,
      "race_count": 21,
      "avg_stops_per_race": 3.5238095238095237,
      "color": "#0090FF",
      "circuitId": 3,
      "circuit": "Bahrain International Circuit",
      "circuit_id": "bahrain-international-circuit"
    },
    {
      "year": 2023,
      "constructorId": 1,
      "constructor": "McLaren",
      "avg_duration_sec": 209.80376595744679,
      "total_stops": 94,
      "race_count": 22,
      "avg_stops_per_race": 4.2727272727272725,
      "color": "#FF8700",
      "circuitId": 3,
      "circuit": "Bahrain International Circuit",
      "circuit_id": "bahrain-international-circuit"
    },
    {
      "year": 2023,
      "constructorId": 3,
      "constructor": "Williams",
      "avg_duration_sec": 120.14877380952382,
      "total_stops": 84,
      "race_count": 22,
      "avg_stops_per_race": 3.8181818181818183,
      "color": "#005AFF",
      "circuitId": 3,
      "circuit": "Bahrain International Circuit",
      "circuit_id": "bahrain-international-circuit"
    },
    {
      "year": 2023,
      "constructorId": 6,
      "constructor": "Ferrari",
      "avg_duration_sec": 152.48709210526314,
      "total_stops": 76,
      "race_count": 22,
      "avg_stops_per_race": 3.4545454545454546,
      "color": "#DC0000",
      "circuitId": 3,
      "circuit": "Bahrain International Circuit",
      "circuit_id": "bahrain-international-circuit"
    },
    {
      "year": 2023,
      "constructorId": 9,
      "constructor": "Red Bull",
      "avg_duration_sec": 208.77005,
      "total_stops": 100,
      "race_count": 22,
      "avg_stops_per_race": 4.545454545454546,
      "color": "#1E41FF",
      "circuitId": 3,
      "circuit": "Bahrain International Circuit",
      "circuit_id": "bahrain-international-circuit"
    },
    {
      "year": 2023,
      "constructorId": 51,
      "constructor": "Alfa Romeo",
      "avg_duration_sec": 170.63210891089108,
      "total_stops": 101,
      "race_count": 22,
      "avg_stops_per_race": 4.590909090909091,
      "color": "#900000",
      "circuitId": 3,
      "circuit": "Bahrain International Circuit",
      "circuit_id": "bahrain-international-circuit"
    },
    {
      "year": 2023,
      "constructorId": 117,
      "constructor": "Aston Martin",
      "avg_duration_sec": 210.52720652173915,
      "total_stops": 92,
      "race_count": 22,
      "avg_stops_per_race": 4.181818181818182,
      "color": "#006F62",
      "circuitId": 3,
      "circuit": "Bahrain International Circuit",
      "circuit_id": "bahrain-international-circuit"
    },
    {
      "year": 2023,
      "constructorId": 131,
      "constructor": "Mercedes",
      "avg_duration_sec": 183.65276923076922,
      "total_stops": 91,
      "race_count": 22,
      "avg_stops_per_race": 4.136363636363637,
      "color": "#00D2BE",
      "circuitId": 3,
      "circuit": "Bahrain International Circuit",
      "circuit_id": "bahrain-international-circuit"
    },
    {
      "year": 2023,
      "constructorId": 210,
      "constructor": "Haas F1 Team",
      "avg_duration_sec": 151.9509893617021,
      "total_stops": 94,
      "race_count": 22,
      "avg_stops_per_race": 4.2727272727272725,
      "color": "#B6BABD",
      "circuitId": 3,
      "circuit": "Bahrain International Circuit",
      "circuit_id": "bahrain-international-circuit"
    },
    {
      "year": 2023,
      "constructorId": 213,
      "constructor": "AlphaTauri",
      "avg_duration_sec": 185.87412631578948,
      "total_stops": 95,
      "race_count": 22,
      "avg_stops_per_race": 4.318181818181818,
      "color": "#2B4562",
      "circuitId": 3,
      "circuit": "Bahrain International Circuit",
      "circuit_id": "bahrain-international-circuit"
    },
    {
      "year": 2023,
      "constructorId": 214,
      "constructor": "Alpine F1 Team",
      "avg_duration_sec": 184.06902352941177,
      "total_stops": 85,
      "race_count": 21,
      "avg_stops_per_race": 4.0476190476190474,
      "color": "#0090FF",
      "circuitId": 3,
      "circuit": "Bahrain International Circuit",
      "circuit_id": "bahrain-international-circuit"
    },
    {
      "year": 2024,
      "constructorId": 1,
      "constructor": "McLaren",
      "avg_duration_sec": 151.3377590361446,
      "total_stops": 83,
      "race_count": 24,
      "avg_stops_per_race": 3.4583333333333335,
      "color": "#FF8700",
      "circuitId": 77,
      "circuit": "Jeddah Corniche Circuit",
      "circuit_id": "jeddah-corniche-circuit"
    },
    {
      "year": 2024,
      "constructorId": 3,
      "constructor": "Williams",
      "avg_duration_sec": 107.87102631578948,
      "total_stops": 76,
      "race_count": 24,
      "avg_stops_per_race": 3.1666666666666665,
      "color": "#005AFF",
      "circuitId": 3,
      "circuit": "Bahrain International Circuit",
      "circuit_id": "bahrain-international-circuit"
    },
    {
      "year": 2024,
      "constructorId": 6,
      "constructor": "Ferrari",
      "avg_duration_sec": 154.51861728395062,
      "total_stops": 81,
      "race_count": 24,
      "avg_stops_per_race": 3.375,
      "color": "#DC0000",
      "circuitId": 3,
      "circuit": "Bahrain International Circuit",
      "circuit_id": "bahrain-international-circuit"
    },
    {
      "year": 2024,
      "constructorId": 9,
      "constructor": "Red Bull",
      "avg_duration_sec": 121.28275294117647,
      "total_stops": 85,
      "race_count": 24,
      "avg_stops_per_race": 3.5416666666666665,
      "color": "#1E41FF",
      "circuitId": 3,
      "circuit": "Bahrain International Circuit",
      "circuit_id": "bahrain-international-circuit"
    },
    {
      "year": 2024,
      "constructorId": 15,
      "constructor": "Sauber",
      "avg_duration_sec": 147.91280459770115,
      "total_stops": 87,
      "race_count": 24,
      "avg_stops_per_race": 3.625,
      "color": "#52E252",
      "circuitId": 3,
      "circuit": "Bahrain International Circuit",
      "circuit_id": "bahrain-international-circuit"
    },
    {
      "year": 2024,
      "constructorId": 117,
      "constructor": "Aston Martin",
      "avg_duration_sec": 131.69893103448274,
      "total_stops": 87,
      "race_count": 24,
      "avg_stops_per_race": 3.625,
      "color": "#006F62",
      "circuitId": 3,
      "circuit": "Bahrain International Circuit",
      "circuit_id": "bahrain-international-circuit"
    },
    {
      "year": 2024,
      "constructorId": 131,
      "constructor": "Mercedes",
      "avg_duration_sec": 150.473,
      "total_stops": 84,
      "race_count": 24,
      "avg_stops_per_race": 3.5,
      "color": "#00D2BE",
      "circuitId": 3,
      "circuit": "Bahrain International Circuit",
      "circuit_id": "bahrain-international-circuit"
    },
    {
      "year": 2024,
      "constructorId": 210,
      "constructor": "Haas F1 Team",
      "avg_duration_sec": 77.05355681818182,
      "total_stops": 88,
      "race_count": 23,
      "avg_stops_per_race": 3.8260869565217392,
      "color": "#B6BABD",
      "circuitId": 3,
      "circuit": "Bahrain International Circuit",
      "circuit_id": "bahrain-international-circuit"
    },
    {
      "year": 2024,
      "constructorId": 214,
      "constructor": "Alpine F1 Team",
      "avg_duration_sec": 132.77298684210524,
      "total_stops": 76,
      "race_count": 24,
      "avg_stops_per_race": 3.1666666666666665,
      "color": "#0090FF",
      "circuitId": 3,
      "circuit": "Bahrain International Circuit",
      "circuit_id": "bahrain-international-circuit"
    },
    {
      "year": 2024,
      "constructorId": 215,
      "constructor": "RB F1 Team",
      "avg_duration_sec": 141.46,
      "total_stops": 78,
      "race_count": 24,
      "avg_stops_per_race": 3.25,
      "color": "#888888",
      "circuitId": 3,
      "circuit": "Bahrain International Circuit",
      "circuit_id": "bahrain-international-circuit"
    }
  ]
}